html_transpose-0.0.8.dist-info/METADATA
html_transpose-0.0.8.dist-info/WHEEL
html_transpose-0.0.8.dist-info/licenses/LICENSE
html_transpose/__init__.py
html_transpose/__init__.pyi
html_transpose/html_transpose.cpython-314-darwin.so
html_transpose/py.typed
html_transpose-0.0.8.dist-info/RECORD
