Metadata-Version: 2.4
Name: html_transpose
Version: 0.0.8
Classifier: Development Status :: 4 - Beta
Classifier: Intended Audience :: Developers
Classifier: License :: OSI Approved :: MIT License
Classifier: Programming Language :: Python :: 3.9
Classifier: Programming Language :: Python :: 3.10
Classifier: Programming Language :: Python :: 3.11
Classifier: Programming Language :: Python :: 3.12
Classifier: Programming Language :: Rust
Classifier: Topic :: Software Development :: Libraries :: Python Modules
Classifier: Topic :: Text Processing :: Markup :: HTML
License-File: LICENSE
Summary: Python wrapper for html_transpose - a Rust library for transposing HTML tables
Keywords: html,table,transpose,rust
Author-email: Sangmin Lee <>
License: MIT
Requires-Python: >=3.9
Project-URL: Homepage, https://github.com/snurf198/html_transpose_py
Project-URL: Repository, https://github.com/snurf198/html_transpose_py
Project-URL: Documentation, https://github.com/snurf198/html_transpose_py#readme
